pddl_embeddings/__init__.py
pddl_embeddings/feature_extractor.py
pddl_embeddings-0.0.2.dist-info/LICENSE.txt
pddl_embeddings-0.0.2.dist-info/METADATA
pddl_embeddings-0.0.2.dist-info/WHEEL
pddl_embeddings-0.0.2.dist-info/top_level.txt
pddl_embeddings-0.0.2.dist-info/RECORD
