Metadata-Version: 2.1
Name: pddl-embeddings
Version: 0.0.2
Summary: A package to extract feature embeddings out of PPDL state text.
Author-email: Victor Dorado Javier <vicdoja@upv.edu.es>
Maintainer-email: Victor Dorado Javier <vicdoja@upv.edu.es>
License: MIT License
Keywords: ppdl,planner,embedding,feature,transformer
Classifier: Development Status :: 3 - Alpha
Classifier: Programming Language :: Python
Classifier: Environment :: GPU :: NVIDIA CUDA
Classifier: License :: OSI Approved :: MIT License
Classifier: Topic :: Scientific/Engineering :: Artificial Intelligence
Requires-Python: >=3.9
License-File: LICENSE.txt
Requires-Dist: transformers
Requires-Dist: numpy
Requires-Dist: torch
